DOMdiff-1.0.2.dist-info/DESCRIPTION.rst
DOMdiff-1.0.2.dist-info/METADATA
DOMdiff-1.0.2.dist-info/RECORD
DOMdiff-1.0.2.dist-info/WHEEL
DOMdiff-1.0.2.dist-info/metadata.json
DOMdiff-1.0.2.dist-info/top_level.txt
domdiff/__init__.py
