Metadata-Version: 2.0
Name: DOMdiff
Version: 1.0.2
Summary: Tool that, given two HTML pages, returns sub-trees of theDOM that got removed and added, respectively.
Home-page: https://github.com/OpenMediaMonitor/domdiff
Author: specialchar
Author-email: specialchar@riseup.net
License: GPLv3
Platform: UNKNOWN
Requires-Dist: beautifulsoup4 (<5,>4.5)
